ansys/api/sherlock/VERSION
ansys/api/sherlock/__init__.py
ansys/api/sherlock/py.typed
ansys/api/sherlock/v0/SherlockAnalysisService.proto
ansys/api/sherlock/v0/SherlockAnalysisService_pb2.py
ansys/api/sherlock/v0/SherlockAnalysisService_pb2.pyi
ansys/api/sherlock/v0/SherlockAnalysisService_pb2_grpc.py
ansys/api/sherlock/v0/SherlockAnalysisService_pb2_grpc.pyi
ansys/api/sherlock/v0/SherlockCommonService.proto
ansys/api/sherlock/v0/SherlockCommonService_pb2.py
ansys/api/sherlock/v0/SherlockCommonService_pb2.pyi
ansys/api/sherlock/v0/SherlockCommonService_pb2_grpc.py
ansys/api/sherlock/v0/SherlockCommonService_pb2_grpc.pyi
ansys/api/sherlock/v0/SherlockLayerService.proto
ansys/api/sherlock/v0/SherlockLayerService_pb2.py
ansys/api/sherlock/v0/SherlockLayerService_pb2.pyi
ansys/api/sherlock/v0/SherlockLayerService_pb2_grpc.py
ansys/api/sherlock/v0/SherlockLayerService_pb2_grpc.pyi
ansys/api/sherlock/v0/SherlockLifeCycleService.proto
ansys/api/sherlock/v0/SherlockLifeCycleService_pb2.py
ansys/api/sherlock/v0/SherlockLifeCycleService_pb2.pyi
ansys/api/sherlock/v0/SherlockLifeCycleService_pb2_grpc.py
ansys/api/sherlock/v0/SherlockLifeCycleService_pb2_grpc.pyi
ansys/api/sherlock/v0/SherlockModelService.proto
ansys/api/sherlock/v0/SherlockModelService_pb2.py
ansys/api/sherlock/v0/SherlockModelService_pb2.pyi
ansys/api/sherlock/v0/SherlockModelService_pb2_grpc.py
ansys/api/sherlock/v0/SherlockModelService_pb2_grpc.pyi
ansys/api/sherlock/v0/SherlockPartsService.proto
ansys/api/sherlock/v0/SherlockPartsService_pb2.py
ansys/api/sherlock/v0/SherlockPartsService_pb2.pyi
ansys/api/sherlock/v0/SherlockPartsService_pb2_grpc.py
ansys/api/sherlock/v0/SherlockPartsService_pb2_grpc.pyi
ansys/api/sherlock/v0/SherlockProjectService.proto
ansys/api/sherlock/v0/SherlockProjectService_pb2.py
ansys/api/sherlock/v0/SherlockProjectService_pb2.pyi
ansys/api/sherlock/v0/SherlockProjectService_pb2_grpc.py
ansys/api/sherlock/v0/SherlockProjectService_pb2_grpc.pyi
ansys_api_sherlock-0.1.53.dist-info/licenses/LICENSE
ansys_api_sherlock-0.1.53.dist-info/METADATA
ansys_api_sherlock-0.1.53.dist-info/WHEEL
ansys_api_sherlock-0.1.53.dist-info/entry_points.txt
ansys_api_sherlock-0.1.53.dist-info/top_level.txt
ansys_api_sherlock-0.1.53.dist-info/RECORD
