Metadata-Version: 2.4
Name: ansys-api-sherlock
Version: 0.1.53
Summary: Autogenerated python gRPC interface package for ansys-api-sherlock, built on 19:11:06 on 04 December 2025
Home-page: https://github.com/ansys/ansys-api-sherlock
Author: ANSYS, Inc.
Author-email: support@ansys.com
License: MIT
Requires-Python: >=3.10
License-File: LICENSE
Requires-Dist: grpcio<1.68.0,~=1.17
Requires-Dist: protobuf<6,>=3.19
Dynamic: author
Dynamic: author-email
Dynamic: description
Dynamic: description-content-type
Dynamic: home-page
Dynamic: license
Dynamic: license-file
Dynamic: requires-dist
Dynamic: requires-python
Dynamic: summary
